Workbook
Name CalcPGBL: #REF!-(VLOOKUP(#REF!-(MAX(0,12%*#REF!-#REF!)),[1]!TabIRAno[#Data],2)*(#REF!-(MAX(0,12%*#REF!-#REF!)))-VLOOKUP(#REF!-(MAX(0,12%*#REF!-#REF!)),[1]!TabIRAno[#Data],3))>#REF!
Name Categorias: #REF!
Name FaltaPGBL: MAX(0,#REF!-#REF!)
Name historico_calculos_Default_2024_05_04: data_ano!$A$1:$O$10
Name historico_calculos_Default_2024_05_04: data_mes!$A$1:$W$77
Name LimDep: [1]Aux!$D$16
Name LimEdu: [1]Aux!$D$19
Name LimSimpl: [1]Aux!$D$13

Sheet data_ano
A1: date | B1: fluxo_ano | C1: fluxo_acc | D1: vlr_investido | E1: vlr_mercado | F1: proventos | G1: yield_pm | H1: yield_vm | I1: ST | J1: DT | K1: lucro | L1: twr_ano | M1: twr_acc | N1: ibov_ano | O1: ibov_acc | P1: selic_ano | Q1: selic_acc
A2: 2018-dez. | B2: 500975.29 | C2: 500975.29 | D2: 511279.1 | E2: 561875.07 | F2: 9615.52 | G2: 0.0256 | H2: 0.0238 | I2: 688.29 | J2: 0 | K2: 60899.79 | L2: 0.3269 | M2: 0.3269 | N2: 0.1503 | O2: 0.1503 | P2: 0.0642 | Q2: 0.0642
A3: 2019-dez. | B3: 120711.73 | C3: 621687.02 | D3: 698115.94 | E3: 941043.95 | F3: 26449.88 | G3: 0.0444 | H3: 0.038 | I3: 39675.23 | J3: 0 | K3: 258457.15 | L3: 0.3958 | M3: 0.8521 | N3: 0.3195 | O3: 0.5178 | P3: 0.0595 | Q3: 0.1275
A4: 2020-dez. | B4: 312492.75 | C4: 934179.77 | D4: 1096060.3 | E4: 1471777.9 | F4: 30704.84 | G4: 0.0342 | H4: 0.0297 | I4: 54744.49 | J4: 2.29 | K4: 218241.16 | L4: 0.1395 | M4: 1.1104 | N4: 0.0288 | O4: 0.5616 | P4: 0.0275 | Q4: 0.1585
A5: 2021-dez. | B5: 192103.1 | C5: 1126282.9 | D5: 1494141.6 | E5: 1743743.6 | F5: 108277.84 | G5: 0.082 | H5: 0.0651 | I5: 97700.31 | J5: 0 | K5: 79862.59 | L5: 0.0498 | M5: 1.2154 | N5: -0.1214 | O5: 0.372 | P5: 0.0444 | Q5: 0.2099
A6: 2022-dez. | B6: -148955.64 | C6: 977327.24 | D6: 1646001.4 | E6: 1733840.2 | F6: 150080.77 | G6: 0.0989 | H6: 0.0873 | I6: 150734.66 | J6: 0 | K6: 139052.31 | L6: 0.0765 | M6: 1.385 | N6: 0.0497 | O6: 0.4402 | P6: 0.1238 | Q6: 0.3597
A7: 2023-dez. | B7: 392540.52 | C7: 1369867.8 | D7: 2311393.7 | E7: 2501052.2 | F7: 84200.74 | G7: 0.0452 | H7: 0.0433 | I7: 188643.25 | J7: 7.84 | K7: 374671.45 | L7: 0.1897 | M7: 1.8374 | N7: 0.2195 | O7: 0.7563 | P7: 0.1303 | Q7: 0.5369
A8: 2024-dez. | B8: -164307.12 | C8: 1205560.6 | D8: 2249043.2 | E8: 2073399.8 | F8: 20753.71 | G8: 0.0094 | H8: 0.0094 | I8: 81202.93 | J8: 0 | K8: -263345.3 | L8: -0.1096 | M8: 1.5264 | N8: -0.1036 | O8: 0.5743 | P8: 0.1089 | Q8: 0.7042
A9: 2025-out. | B9: 18469.23 | C9: 1220469.8 | D9: 2296479.6 | E9: 2550670.5 | F9: 23891 | G9: 0.0104 | H9: 0.0099 | I9: 5076.16 | J9: 0 | K9: 458801.52 | L9: 0.2155 | M9: 2.0758 | N9: 0.2494 | O9: 0.967 | P9: 0.1185 | Q9: 0.9061

Sheet data_mes
A1: date | B1: vlr_investido | C1: vlr_mercado | D1: lucro | E1: proventos | F1: volume | G1: fluxo_mes | H1: fluxo_acc | I1: lucro_mes | J1: twr_mes | K1: ibov_mes | L1: ifix_mes | M1: selic_mes | N1: ipca_mes | O1: ivvb_mes | P1: twr_acc | Q1: ibov_acc | R1: ifix_acc | S1: selic_acc | T1: ipca_acc | U1: ivvb_acc | V1: yield_pm | W1: yield_vm
A2: 43131 | B2: 70504.52 | C2: 82244.3 | D2: 0 | E2: 0 | F2: 0 | G2: 70504.52 | H2: 70504.52 | I2: 11739.78 | J2: 0.16651103 | K2: 0.11139761 | L2: 0.026396163 | M2: 0.0058 | N2: 0.0029 | O2: 0.0080171032 | P2: 0.16651103 | Q2: 0.11139761 | R2: 0.026396163 | S2: 0.0058 | T2: 0.0029 | U2: 0.0080171032 | V2: 0 | W2: 0
A3: 43159 | B3: 105838.47 | C3: 117452.38 | D3: 0 | E3: 0 | F3: 0 | G3: 35333.95 | H3: 105838.47 | I3: -125.87 | J3: -0.0010705211 | K3: 0.0066891995 | L3: 0.011456177 | M3: 0.0047 | N3: 0.0032 | O3: -0.018027572 | P3: 0.16526225 | Q3: 0.11883197 | R3: 0.038154739 | S3: 0.01052726 | T3: 0.00610928 | U3: -0.010154997 | V3: 0 | W3: 0
A4: 43190 | B4: 107227.33 | C4: 118973.67 | D4: 0 | E4: 0 | F4: 0 | G4: 1388.86 | H4: 107227.33 | I4: 132.43 | J4: 0.0011143438 | K4: -0.0013453282 | L4: 0.019957515 | M4: 0.0053 | N4: 0.0009 | O4: -0.010151188 | P4: 0.16656075 | Q4: 0.11732677 | R4: 0.058873728 | S4: 0.015883054 | T4: 0.0070147784 | U4: -0.0202031 | V4: 0 | W4: 0
A5: 43220 | B5: 127459.56 | C5: 144740.31 | D5: 0 | E5: 45.25 | F5: 0 | G5: 20186.98 | H5: 127414.31 | I5: 5579.66 | J5: 0.040095099 | K5: 0.008773985 | L5: -0.0086064287 | M5: 0.0052 | N5: 0.0022 | O5: 0.064804713 | P5: 0.21333412 | Q5: 0.12713018 | R5: 0.049760607 | S5: 0.021165646 | T5: 0.0092302109 | U5: 0.043292357 | V5: 0.00035501456 | W5: 0.00031262887
A6: 43251 | B6: 167965.39 | C6: 183258.87 | D6: 0 | E6: 100.2 | F6: 0 | G6: 40405.63 | H6: 167819.94 | I6: -1887.07 | J6: -0.010192338 | K6: -0.10870348 | L6: -0.052685849 | M6: 0.0052 | N6: 0.004 | O6: 0.10010246 | P6: 0.20096741 | Q6: 0.0046072092 | R6: -0.005546922 | S6: 0.026475708 | T6: 0.013267132 | U6: 0.14772849 | V6: 0.00059655147 | W6: 0.00054676753
A7: 43281 | B7: 229844.46 | C7: 244360.67 | D7: -280.49 | E7: 348.8 | F7: 3687.6 | G7: 61810.76 | H7: 229630.7 | I7: -708.96 | J7: -0.0028928921 | K7: -0.05199729 | L7: -0.040147057 | M7: 0.0052 | N7: 0.0126 | O7: 0.033808326 | P7: 0.19749314 | Q7: -0.047629643 | R7: -0.045471286 | S7: 0.031813381 | T7: 0.026034298 | U7: 0.18653127 | V7: 0.001517548 | W7: 0.0014273983
A8: 43312 | B8: 274220.25 | C8: 287745.1 | D8: 0 | E8: 780.26 | F8: 0 | G8: 43595.53 | H8: 273226.23 | I8: -211.1 | J8: -0.0007330976 | K8: 0.088740156 | L8: 0.013749165 | M8: 0.0054 | N8: 0.0033 | O8: 0.0052252252 | P8: 0.19661526 | Q8: 0.036883851 | R8: -0.032347314 | S8: 0.037385174 | T8: 0.029420211 | U8: 0.19273116 | V8: 0.002845377 | W8: 0.0027116361
A9: 43343 | B9: 324859.49 | C9: 343845.07 | D9: 193.8216 | E9: 1471.98 | F9: 11656.91 | G9: 48973.44 | H9: 322199.67 | I9: 7126.53 | J9: 0.02116465 | K9: -0.032087857 | L9: -0.006985574 | M9: 0.0057 | N9: -0.0009 | O9: 0.12206489 | P9: 0.22194121 | Q9: 0.0036124709 | R9: -0.039106923 | S9: 0.043298269 | T9: 0.028493733 | U9: 0.33832175 | V9: 0.0045311282 | W9: 0.0042809397
A10: 43373 | B10: 329830.14 | C10: 347516.99 | D10: 85.7 | E10: 1090.44 | F10: 6607.1 | G10: 3794.51 | H10: 325994.18 | I10: -122.59 | J10: -0.00035263534 | K10: 0.03474269 | L10: -0.0021454714 | M10: 0.0047 | N10: 0.0048 | O10: -0.0087859425 | P10: 0.22151031 | Q10: 0.038480668 | R10: -0.041168492 | S10: 0.048201771 | T10: 0.033430502 | U10: 0.32656334 | V10: 0.0033060653 | W10: 0.0031378034
A11: 43404 | B11: 394270.76 | C11: 429115.68 | D11: 297.96 | E11: 1094.53 | F11: 25659.6 | G11: 63048.13 | H11: 389042.31 | I11: 18550.56 | J11: 0.045182991 | K11: 0.10186282 | L11: 0.050421585 | M11: 0.0054 | N11: 0.0045 | O11: -0.138195 | P11: 0.2767018 | Q11: 0.14426324 | R11: 0.0071773129 | S11: 0.053862061 | T11: 0.03808094 | U11: 0.14323891 | V11: 0.0027760872 | W11: 0.0025506642
A12: 43434 | B12: 481641.65 | C12: 522815.57 | D12: 13.657 | E12: 2081.6 | F12: 26255.5 | G12: 85275.63 | H12: 474317.94 | I12: 8424.26 | J12: 0.016377143 | K12: 0.023792094 | L12: 0.025878061 | M12: 0.0049 | N12: -0.0021 | O12: 0.055633474 | P12: 0.29761052 | Q12: 0.17148766 | R12: 0.033241109 | S12: 0.059025985 | T12: 0.03590097 | U12: 0.20684126 | V12: 0.0043218854 | W12: 0.0039815188
A13: 43465 | B13: 511279.1 | C13: 561875.07 | D13: 377.63974 | E13: 2602.46 | F13: 24203.19 | G13: 26657.348 | H13: 500975.29 | I13: 12402.156 | J13: 0.022571005 | K13: -0.018066232 | L13: 0.022221546 | M13: 0.0049 | N13: 0.0015 | O13: -0.090345438 | P13: 0.3268989 | Q13: 0.15032329 | R13: 0.056201324 | S13: 0.064215212 | T13: 0.037454821 | U13: 0.097808658 | V13: 0.0050900966 | W13: 0.0046317413
... A95: 45961 | B95: 2296479.6 | C95: 2553823.6 | D95: -299.31187 | E95: 10000 | F95: 31370.833 | G95: -39394.039 | H95: 1220469.8 | I95: 42861.662 | J95: 0.016806149 | K95: 0.022586623 | L95: 0.0011534214 | M95: 0.0128 | N95: 0.0048 | O95: 0.033841921 | P95: 2.0796312 | Q95: 0.95727861 | R95: 0.61403307 | S95: 0.90498508 | T95: 0.50399882 | U95: 3.4269498 | V95: 0.0043544911 | W95: 0.0039156973

Sheet data_port_historico
A1: Tipo | B1: Categoria | C1: Alocação | D1: 45261 | E1: 45292 | F1: 45323 | G1: 45352 | H1: 45383 | I1: 45413 | J1: 45627 | K1: 45778 | L1: 45809 | M1: 45839 | N1: 45870 | O1: 45960
A2: Ativos Financeiros | B2: R.Fixa | C2: RF_Inflação | D2: 248811.88 | E2: 269742.86 | F2: 195060.68 | G2: 194570.44 | H2: 192301.82 | I2: 196245.2 | J2: =164221.974642042+J10+(J12*60%) -> 268050.51 | K2: =176664.263036861+K10+(K12*60%) -> 295157.63 | L2: =180165.3967+L10+(L12*60%) -> 306116.65 | M2: =103183.24+M10+(M12*60%) -> 227995.03 | N2: 226439.08 | O2: 231983.37
A3: Ativos Financeiros | B3: R.Fixa | C3: RF_CDI | D3: 74535.41 | E3: 78438.74 | F3: 5077.87 | G3: 21717.79 | H3: 22795.19 | I3: 10004.049 | J3: 0 | K3: 44477.38 | L3: 37395.55 | M3: 39753.89 | N3: 18878.67 | O3: 14237.31
A4: Ativos Financeiros | B4: R.Fixa | C4: RF_Infra | D4: 27500 | E4: 26535 | F4: 26537.5 | G4: 26650 | H4: 26475 | I4: 28045 | J4: 56118 | K4: 66917.76 | L4: 65627.52 | M4: 96100 | N4: 96970 | O4: 98070
A5: Ativos Financeiros | B5: R.Variável | C5: RV_Ações | D5: 382978.72 | E5: 265579 | F5: 228213 | G5: 200627 | H5: 57017 | I5: 0 | J5: =J11 -> 155667.47 | K5: =K11 -> 194623.82 | L5: =L11 -> 196185.87 | M5: =M11 -> 184313.08 | N5: 198279.17 | O5: 204774
A6: Ativos Financeiros | B6: R.Variável | C6: RV_FII | D6: 90200 | E6: 85690 | F6: 82335 | G6: 85030 | H6: 84029 | I6: 83380 | J6: 69267 | K6: 68900 | L6: 68090 | M6: 83227.5 | N6: 82957.5 | O6: 78975
A7: Ativos Financeiros | B7: R.Variável | C7: RV_Clube | D7: 1278698.2 | E7: 1183682.8 | F7: 1271052.6 | G7: 1328348.1 | H7: 1341279.7 | I7: 1410717 | J7: 1336738.9 | K7: 1483579.4 | L7: 1555586.3 | M7: 1481053.8 | N7: 1579852.6 | O7: 1684406.1
A8: Ativos Financeiros | B8: Cripto | C8: Cripto_Token | D8: 14747.2 | E8: 15135.01 | F8: 24086.81 | G8: 23317.17 | H8: 20362.06 | I8: 26293.095 | M8: 0
A9: Ativos Financeiros | B9: Cripto | C9: Cripto_ETF | D9: 0 | E9: 0 | F9: 0 | G9: 0 | H9: 0 | K9: 8159 | L9: 8068 | M9: 8673 | N9: 8849 | O9: 7437
A10: Ativos Financeiros | B10: Previdencia | C10: Prev_Inflação | D10: 7155.71 | E10: 7220.29 | F10: 7237.44 | G10: 10329.2 | H10: 10222.53 | I10: 11255.308 | J10: 80682.197 | K10: 93251.768 | L10: 98315.671 | M10: 97149.662 | N10: 0 | O10: 0
A11: Ativos Financeiros | B11: Previdencia | C11: Prev_FIA | D11: 212142.2 | E11: 202994.53 | F11: 189909.37 | G11: 205805.85 | H11: 194949.12 | I11: 191916.79 | J11: 155667.47 | K11: 194623.82 | L11: 196185.87 | M11: 184313.08 | N11: 0 | O11: 0
A12: Ativos Financeiros | B12: Previdencia | C12: Bogleprev | D12: 27421.61 | E12: 27465.13 | F12: 27956.29 | G12: 31225.51 | H12: 30943.07 | I12: 32416.798 | J12: 38577.225 | K12: 42069.324 | L12: 46059.309 | M12: 46103.539 | N12: 0 | O12: 0
A13: Ativos Financeiros | B13: Previdencia | C13: FGTS | D13: 43903.11 | E13: 46211.71 | F13: 48095.24 | G13: 49946.69 | H13: 46373.43 | I13: 48277.5 | J13: 65260.55 | K13: 68739.99 | L13: 73357.02 | M13: 77013.07 | N13: 79355.7 | O13: 84066.55
A14: Ativos Financeiros | B14: Exterior | C14: RV WD_All | D14: 78351.09 | E14: 81749.73 | F14: 84120.57 | G14: 88306.78 | H14: 86580.42 | I14: 91280.601 | J14: =117153.920027056+(J12*40%) -> 132584.81 | K14: =118856.327096289+(K12*40%) -> 135684.06 | L14: =122877.748290939+(L12*40%) -> 141301.47 | M14: =121647.52+(M12*40%) -> 140088.94 | N14: 18492.446 | O14: 19100.112
A15: Ativos Financeiros | B15: Exterior | C15: RF US_Bond | D15: 14578.59 | E15: 14997.21 | F15: 15012.21 | G15: 15373.76 | H15: 15477.72 | I15: 16099.544 | J15: 0 | K15: 0 | L15: 10397.067 | M15: 10291.641 | N15: 26885.59 | O15: 0
A16: Ativos Financeiros | B16: Exterior | C16: RV WD_Dev | N16: 78049.204 | O16: 80953.575
A17: Ativos Financeiros | B17: Exterior | C17: RV WD_Factor | N17: 20197.039 | O17: 20822.627
A18: Ativos Financeiros | B18: Exterior | C18: RV WD_Quality | N18: 11456.702 | O18: 11706.306
A19: Ativos Financeiros | B19: Exterior | C19: RV WD_LowVol | N19: 9764.0485 | O19: 9525.4452
A20: Ativos Financeiros | B20: Exterior | C20: RV WD_Emerging | N20: 4213.1364 | O20: 4613.153
A21: Ativos Imobilizados | B21: Imoveis | C21: Sobrado Neoville | D21: 700000 | E21: 700000 | F21: 700000 | G21: 700000 | H21: 700000 | I21: 700000 | J21: 800000 | K21: 800000 | L21: 800000 | M21: 800000 | N21: 800000 | O21: 800000
A22: Ativos Imobilizados | B22: Veiculos | C22: AUX-1J96 - Focus | D22: 50000 | E22: 50000 | F22: 50000 | G22: 50000 | H22: 50000 | I22: 50000 | J22: 53500 | K22: 52000 | L22: 50000 | M22: 50000 | N22: 50000 | O22: 50000
A23: Ativos Imobilizados | B23: Veiculos | C23: BEX-9H99 - HR-V | D23: 120000 | E23: 120000 | F23: 120000 | G23: 120000 | H23: 120000 | I23: 120000 | J23: 111000 | K23: 110000 | L23: 110000 | M23: 110000 | N23: 110000 | O23: 110000
A24: Ativos Imobilizados | B24: Imoveis | C24: Landscape D28 | F24: 165000 | G24: 165000 | H24: 165000 | I24: 235000 | J24: 260000 | K24: 275000 | L24: 312596.13 | M24: 339649.12 | N24: 354000 | O24: 365800
A25: Ativos Imobilizados | B25: Imoveis | C25: Cipriano I05 | O25: 0

Sheet data_port_mes
A1: ativo | B1: qtd | C1: pm | D1: pm_fx | E1: pm_usd | F1: corretora | G1: classe | H1: market_cod | I1: moeda | J1: setor | K1: subsetor | L1: vlr_investido | M1: fator_pts | N1: price | O1: change | P1: changepct | Q1: price_fx | R1: change_fx | S1: changepct_fx | T1: earnings | U1: trades | V1: xirr | W1: xirr_grouped | X1: date_ini | Y1: nome_pregao | Z1: vlr_mercado | AA1: lucro_total | AB1: lucro_total_pct | AC1: lucro_dia | AD1: lucro_dia_pct | AE1: carteira | AF1: Nome | AG1: Tipo | AH1: Liquidez
A2: HASH11 | B2: 100 | C2: 60.33 | D2: 60.33 | E2: 10.16204 | F2: MAR | G2: ETF | H2: BVMF:HASH11 | I2: BRL | J2: OUTROS | K2: FUNDOS | L2: 6033 | M2: 1 | N2: 74.37 | O2: -4.24 | P2: -5.39 | Q2: 0 | R2: 0 | S2: 0 | T2: 0 | U2: 0 | V2: 43.857026 | W2: 0 | X2: 45755 | Y2: HASHDEX NCI CI | Z2: 7437 | AA2: 1404 | AB2: 23.272004 | AC2: -424 | AD2: -5.3937158 | AE2: ["Cripto"] | AF2: =VLOOKUP(A2,Referencias!A:D,2,0) -> HASH11 | AG2: =VLOOKUP(A2,Referencias!A:D,3,0) -> Cripto_ETF | AH2: =VLOOKUP(A2,Referencias!A:D,4,0) -> D+2
A3: EIMI | B3: 19 | C3: 146.77064 | D3: 29.36 | E3: 29.36 | F3: MAR | G3: ETF_GB | H3: LON:EIMI | I3: USD | J3: ETF GB | K3: ISHARES CORE MSCI EM IMI UCITS ETF | L3: 2788.6422 | M3: 1 | N3: 242.79753 | O3: 0.29100882 | P3: 0.12000041 | Q3: 44.99 | R3: -0.13 | S3: -0.29 | T3: 0 | U3: 0 | V3: 22.815028 | W3: 0 | X3: 45071 | Y3: EIMI.L | Z3: 4613.153 | AA3: 1824.5109 | AB3: 65.426497 | AC3: 5.5291676 | AD3: 0.12000041 | AE3: ["RV Exterior"] | AF3: =VLOOKUP(A3,Referencias!A:D,2,0) -> EIMI | AG3: =VLOOKUP(A3,Referencias!A:D,3,0) -> RV WD_Emerging | AH3: =VLOOKUP(A3,Referencias!A:D,4,0) -> Sem
A4: IFSW | B4: 280 | C4: 47.149564 | D4: 8.9739643 | E4: 8.9739643 | F4: MAR | G4: ETF_GB | H4: LON:IFSW | I4: USD | J4: ETF GB | K4: ISHARES IV PLC ISHS EDGE MSCI WRLD MULTIFAC ETF | L4: 13201.878 | M4: 1 | N4: 74.366525 | O4: -0.15001327 | P4: -0.20131541 | Q4: 13.78 | R4: -0.09 | S4: -0.61 | T4: 0 | U4: 0 | V4: 22.934001 | W4: 0 | X4: 44957 | Y4: IFSW.L | Z4: 20822.627 | AA4: 7620.749 | AB4: 57.724735 | AC4: -42.003716 | AD4: -0.20131541 | AE4: ["RV Exterior"] | AF4: =VLOOKUP(A4,Referencias!A:D,2,0) -> IFSW | AG4: =VLOOKUP(A4,Referencias!A:D,3,0) -> RV WD_Factor | AH4: =VLOOKUP(A4,Referencias!A:D,4,0) -> Sem
A5: IWDA | B5: 117 | C5: 422.42979 | D5: 82.780855 | E5: 82.780855 | F5: MAR | G5: ETF_GB | H5: LON:IWDA | I5: USD | J5: ETF GB | K5: ISHARES CORE MSCI WORLD UCITS ETF USD | L5: 49424.285 | M5: 1 | N5: 691.91089 | O5: -1.8145229 | P5: -0.26156212 | Q5: 128.21 | R5: -0.86 | S5: -0.67 | T5: 0 | U5: 0 | V5: 12.832662 | W5: 0 | X5: 44349 | Y5: IWDA.L | Z5: 80953.575 | AA5: 31529.289 | AB5: 63.793111 | AC5: -212.29918 | AD5: -0.26156212 | AE5: ["RV Exterior"] | AF5: =VLOOKUP(A5,Referencias!A:D,2,0) -> IWDA | AG5: =VLOOKUP(A5,Referencias!A:D,3,0) -> RV WD_Dev | AH5: =VLOOKUP(A5,Referencias!A:D,4,0) -> Sem
A6: IWQU | B6: 28 | C6: 289.59915 | D6: 52.8075 | E6: 52.8075 | F6: MAR | G6: ETF_GB | H6: LON:IWQU | I6: USD | J6: ETF GB | K6: ISHARES EDGE MSCI WORLD QUALITY FACTOR UCITS ETF | L6: 8108.7762 | M6: 1 | N6: 418.08234 | O6: -0.29613186 | P6: -0.070780855 | Q6: 77.47 | R6: -0.37 | S6: -0.48 | T6: 0 | U6: 0 | V6: 19.908333 | W6: 0 | X6: 44977 | Y6: IWQU.L | Z6: 11706.306 | AA6: 3597.5293 | AB6: 44.365873 | AC6: -8.2916921 | AD6: -0.070780855 | AE6: ["RV Exterior"] | AF6: =VLOOKUP(A6,Referencias!A:D,2,0) -> IWQU | AG6: =VLOOKUP(A6,Referencias!A:D,3,0) -> RV WD_Quality | AH6: =VLOOKUP(A6,Referencias!A:D,4,0) -> Sem
A7: ACWV | B7: 15 | C7: 488.34492 | D7: 97.083333 | E7: 97.083333 | F7: MAR | G7: ETF_US | H7: BATS:ACWV | I7: USD | J7: ETF US | K7: LARGE CAP BLEND EQUITIES | L7: 7325.1738 | M7: 1 | N7: 635.02968 | O7: 1.6504348 | P7: 0.26057608 | Q7: 117.67 | R7: -0.21 | S7: -0.15 | T7: 0 | U7: 0 | V7: 10.384414 | W7: 0 | X7: 44958 | Y7: ISHARES MSCI ALL COUNTRY WORLD MINIMUM VOLATILITY ETF | Z7: 9525.4452 | AA7: 2200.2714 | AB7: 30.037122 | AC7: 24.756522 | AD7: 0.26057608 | AE7: ["RV Exterior"] | AF7: =VLOOKUP(A7,Referencias!A:D,2,0) -> ACWV | AG7: =VLOOKUP(A7,Referencias!A:D,3,0) -> RV WD_LowVol | AH7: =VLOOKUP(A7,Referencias!A:D,4,0) -> Sem
A8: IRDM11 | B8: 1350 | C8: 90.319762 | D8: 90.319762 | E8: 17.639569 | F8: PAI | G8: FII | H8: BVMF:IRDM11 | I8: BRL | J8: FUNDO DE PAPEL | K8: CRIS | L8: 121931.68 | M8: 1 | N8: 58.5 | O8: 0 | P8: 0 | Q8: 0 | R8: 0 | S8: 0 | T8: 59947.19 | U8: 14161.449 | V8: 8.1370816 | W8: 0 | X8: 43341 | Y8: FII IRIDIUM CI | Z8: 78975 | AA8: -42956.679 | AB8: -35.230122 | AC8: 0 | AD8: 0 | AE8: ["RV Brasil"] | AF8: =VLOOKUP(A8,Referencias!A:D,2,0) -> IRDM11 | AG8: =VLOOKUP(A8,Referencias!A:D,3,0) -> RV_FII | AH8: =VLOOKUP(A8,Referencias!A:D,4,0) -> D+2
A9: JURO11 | B9: 1000 | C9: 96.50201 | D9: 96.50201 | E9: 17.206884 | F9: MAR | G9: FI_INFRA | H9: BVMF:JURO11 | I9: BRL | J9: FINANCEIRO | K9: FUNDOS | L9: 96502.01 | M9: 1 | N9: 98.07 | O9: -0.43 | P9: -0.44 | Q9: 0 | R9: 0 | S9: 0 | T9: 22372.5 | U9: 0 | V9: 22.575539 | W9: 0 | X9: 45000 | Y9: SPARTA INFRA FIDC | Z9: 98070 | AA9: 1567.99 | AB9: 1.6248263 | AC9: -430 | AD9: -0.43654822 | AE9: ["R,Fixa"] | AF9: =VLOOKUP(A9,Referencias!A:D,2,0) -> JURO11 | AG9: =VLOOKUP(A9,Referencias!A:D,3,0) -> RF_Infra | AH9: =VLOOKUP(A9,Referencias!A:D,4,0) -> D+2
A10: CVM:38173778000175 | B10: 345941.2 | C10: 0.60952493 | D10: 0.60952493 | E10: 0.119416 | F10: MAR | G10: FUNDO | H10: CVM:38173778000175 | I10: BRL | J10: AÇÕES | K10: INDEFINIDO | L10: 210859.78 | M10: 1 | N10: 0.5478586 | O10: 0.0016375 | P10: 0.29978703 | Q10: 0 | R10: 0 | S10: 0 | T10: 0 | U10: -1800.6137 | V10: -3.0831051 | W10: 0 | X10: 44396 | Y10: BOGARI VALUE Q ACCESS PREV FIC D | Z10: 189526.86 | AA10: -21332.925 | AB10: -10.117114 | AC10: 566.47871 | AD10: 0.29978703 | AE10: ["RV Brasil"] | AF10: =VLOOKUP(A10,Referencias!A:D,2,0) -> BOGARI VALUE Q | AG10: =VLOOKUP(A10,Referencias!A:D,3,0) -> Prev_FIA | AH10: =VLOOKUP(A10,Referencias!A:D,4,0) -> Sem
A11: CVM:42357379000131 | B11: 31987.54 | C11: 1.2174777 | D11: 1.2174777 | E11: 0.21401263 | F11: MAR | G11: FUNDO | H11: CVM:42357379000131 | I11: BRL | J11: RENDA FIXA | K11: ÍNDICE DE MERCADO ANDIMA NTN-B MAIS DE 5 ANOS | L11: 38944.118 | M11: 1 | N11: 1.2900746 | O11: -0.00077083376 | P11: -0.059715419 | Q11: 0 | R11: 0 | S11: 0 | T11: 0 | U11: 0 | V11: 5.7221603 | W11: 0 | X11: 45468 | Y11: BTG PACTUAL NTN-B 2035 YIELD PRE | Z11: 41266.313 | AA11: 2322.1947 | AB11: 5.9628894 | AC11: -24.657076 | AD11: -0.059715419 | AE11: ["R,Fixa"] | AF11: =VLOOKUP(A11,Referencias!A:D,2,0) -> BTG NTN-B 2035 PREV | AG11: =VLOOKUP(A11,Referencias!A:D,3,0) -> Prev_Inflação | AH11: =VLOOKUP(A11,Referencias!A:D,4,0) -> Sem
A12: CVM:44027256000168 | B12: 35703.565 | C12: 1.1016127 | D12: 1.1016127 | E12: 0.21769601 | F12: MAR | G12: FUNDO | H12: CVM:44027256000168 | I12: BRL | J12: MULTIMERCADO | K12: NÃO SE APLICA | L12: 39331.501 | M12: 1 | N12: 1.3374093 | O12: 0.0034461 | P12: 0.25833546 | Q12: 0 | R12: 0 | S12: 0 | T12: 0 | U12: 0 | V12: 10.920123 | W12: 0 | X12: 45091 | Y12: EMPIRICUS GLOBAL REAL RETURN PRE | Z12: 47750.28 | AA12: 8418.7787 | AB12: 21.404672 | AC12: 123.03806 | AD12: 0.25833546 | AE12: ["R,Fixa"] | AF12: =VLOOKUP(A12,Referencias!A:D,2,0) -> BOGLEPREV | AG12: =VLOOKUP(A12,Referencias!A:D,3,0) -> Prev_FIM | AH12: =VLOOKUP(A12,Referencias!A:D,4,0) -> Sem
A13: CVM:48373538000178 | B13: 15399.859 | C13: 1.092911 | D13: 1.092911 | E13: 0.21944241 | F13: MAR | G13: FUNDO | H13: CVM:48373538000178 | I13: BRL | J13: FMP-FGTS | K13: NÃO SE APLICA | L13: 16830.675 | M13: 1 | N13: 0.99008333 | O13: 0.0073870974 | P13: 0.75171729 | Q13: 0 | R13: 0 | S13: 0 | T13: 0 | U13: 0 | V13: -5.5214008 | W13: 0 | X13: 45330 | Y13: BTG PACTUAL REFERENCE ABSOLUTO F | Z13: 15247.143 | AA13: -1583.5315 | AB13: -9.4086038 | AC13: 113.76026 | AD13: 0.75171729 | AE13: ["RV Brasil"] | AF13: =VLOOKUP(A13,Referencias!A:D,2,0) -> BTG FMP CARTEIRA LIVRE | AG13: =VLOOKUP(A13,Referencias!A:D,3,0) -> Prev_FIA | AH13: =VLOOKUP(A13,Referencias!A:D,4,0) -> Sem
... A18: TD:IPCA2045 | B18: 40.139993 | C18: 1021.1238 | D18: 1021.1238 | E18: 186.28595 | F18: MAR | G18: R.FIXA | H18: TD:IPCA2045 | I18: BRL | J18: TIT.PUBLICO | K18: IPCA | L18: 40987.901 | M18: 1 | N18: 1172.99 | O18: -3.76 | P18: -0.31952411 | Q18: 0 | R18: 0 | S18: 0 | T18: 0 | U18: 0 | V18: 5.7047606 | W18: 0 | X18: 44768 | Y18: TESOURO IPCA | Z18: 47083.81 | AA18: 6095.9087 | AB18: 14.872459 | AC18: -150.92637 | AD18: -0.31952411 | AE18: ["R,Fixa"] | AF18: =VLOOKUP(A18,Referencias!A:D,2,0) -> TD:IPCA2045 | AG18: =VLOOKUP(A18,Referencias!A:D,3,0) -> RF_Inflação | AH18: =VLOOKUP(A18,Referencias!A:D,4,0) -> D+1
A19: TESOURO SELIC | B19: 947.68254 | C19: 14.02123 | D19: 14.02123 | E19: 2.4667161 | F19: MAR | G19: R.FIXA | H19: OUTROS:TESOURO SELIC | I19: BRL | J19: OUTROS | K19: SELIC | L19: 13287.674 | M19: 1 | N19: 15.02329 | O19: 0 | P19: 0 | Q19: 0 | R19: 0 | S19: 0 | T19: 0 | U19: 1638.8445 | V19: 12.455691 | W19: 0 | X19: 45665 | Y19: TESOURO SELIC | Z19: 14237.31 | AA19: 949.63551 | AB19: 7.1467397 | AC19: 0 | AD19: 0 | AF19: =VLOOKUP(A19,Referencias!A:D,2,0) -> TESOURO SELIC | AG19: =VLOOKUP(A19,Referencias!A:D,3,0) -> RF_CDI | AH19: =VLOOKUP(A19,Referencias!A:D,4,0) -> D+0
A20: MLUCA-ELO | B20: 759375.56 | C20: 1.0074177 | D20: 1.0074177 | E20: 0.20558122 | F20: ELO | G20: R.VARIAVEL | H20: OUTROS:MLUCA-ELO | I20: BRL | J20: CLUBE | K20: IBOV | L20: 765008.37 | M20: 1 | N20: 1.1786914 | O20: 0 | P20: 0 | Q20: 0 | R20: 0 | S20: 0 | T20: 0 | U20: 0 | V20: 7.8254167 | W20: 0 | X20: 45086 | Y20: MLUCA-ELO | Z20: 895069.45 | AA20: 130061.08 | AB20: 17.001262 | AC20: 0 | AD20: 0 | AE20: ["RV Brasil"] | AF20: =VLOOKUP(A20,Referencias!A:D,2,0) -> MLUCA-ELO | AG20: =VLOOKUP(A20,Referencias!A:D,3,0) -> RV_Clube | AH20: =VLOOKUP(A20,Referencias!A:D,4,0) -> D+7
A21: MLUCA-MAR | B21: 685722.74 | C21: 0.99993758 | D21: 0.99993758 | E21: 0.20543732 | F21: MAR | G21: R.VARIAVEL | H21: OUTROS:MLUCA-MAR | I21: BRL | J21: CLUBE | K21: IBOV | L21: 685679.94 | M21: 1 | N21: 1.1511017 | O21: 0 | P21: 0 | Q21: 0 | R21: 0 | S21: 0 | T21: 0 | U21: 0 | V21: 6.7087951 | W21: 0 | X21: 45086 | Y21: MLUCA-MAR | Z21: 789336.63 | AA21: 103656.69 | AB21: 15.117358 | AC21: 0 | AD21: 0 | AE21: ["RV Brasil"] | AF21: =VLOOKUP(A21,Referencias!A:D,2,0) -> MLUCA-MAR | AG21: =VLOOKUP(A21,Referencias!A:D,3,0) -> RV_Clube | AH21: =VLOOKUP(A21,Referencias!A:D,4,0) -> D+7

Sheet Referencias
A1: Ativo | B1: Nome | C1: Tipo | D1: Liquidez | I1: data_ano | J1: extrato do dashboard dlombello app com filtro por ano
A2: MLUCA-ELO | B2: MLUCA-ELO | C2: RV_Clube | D2: D+7 | I2: data_mes | J2: extrato do dashboard dlombello app com filtro por mês
A3: MLUCA-MAR | B3: MLUCA-MAR | C3: RV_Clube | D3: D+7 | I3: data_port_historico | J3: calculo original deve ser feito no excel, pois as prevs são redistribuidas conforme a alocação dos fundos (exterior, rf, rv, etc)
A4: CVM:38173778000175 | B4: BOGARI VALUE Q | C4: Prev_FIA | D4: Sem | I4: data_por_mes | J4: copia e cola do dlombello app. Não distribui as prevs, por isso os valores serao diferentes do "historico"
A5: IRDM11 | B5: IRDM11 | C5: RV_FII | D5: D+2
A6: IWDA | B6: IWDA | C6: RV WD_Dev | D6: Sem
A7: FGTS | B7: FGTS | C7: FGTS | D7: Sem
A8: TD:IPCA2045 | B8: TD:IPCA2045 | C8: RF_Inflação | D8: D+1
A9: CVM:44027256000168 | B9: BOGLEPREV | C9: Prev_FIM | D9: Sem
A10: JURO11 | B10: JURO11 | C10: RF_Infra | D10: D+2
A11: TD:IPCA2035 | B11: TD:IPCA2035 | C11: RF_Inflação | D11: D+1
A12: HASH11 | B12: HASH11 | C12: Cripto_ETF | D12: D+2
A13: CVM:48373538000178 | B13: BTG FMP CARTEIRA LIVRE | C13: Prev_FIA | D13: Sem
A14: IFSW | B14: IFSW | C14: RV WD_Factor | D14: Sem
A15: ACWV | B15: ACWV | C15: RV WD_LowVol | D15: Sem
A16: IWQU | B16: IWQU | C16: RV WD_Quality | D16: Sem
... A21: CVM:54248765000174 | B21: BTG NTN-B 2045 PREV | C21: Prev_Inflação | D21: Sem
